Metadata-Version: 2.1
Name: slp-coroutine
Version: 0.0.2
Summary: Convert plain old functions to coroutines and vice versa
Home-page: https://github.com/akruis/slp_coroutine
Author: Anselm Kruis
Author-email: anselm@kruis.de
License: UNKNOWN
Project-URL: Bug Tracker, https://github.com/akruis/slp_coroutine/issues
Platform: UNKNOWN
Classifier: Programming Language :: Python :: Implementation :: Stackless
Classifier: Programming Language :: Python :: 3
Classifier: Programming Language :: Python :: 3.7
Classifier: License :: OSI Approved :: GNU Lesser General Public License v2 or later (LGPLv2+)
Classifier: Operating System :: OS Independent
Classifier: Framework :: AsyncIO
Requires-Python: >=3.7.6
License-File: LICENSE
